{
  "inputGroupClasses": {
    "type": "css-class",
    "staticClasses": ["input-group"],
    "optionalClasses": [
      {
        "label": "Input size",
        "type": "enum",
        "options": [
          {
            "label": "Large",
            "value": "input-group-lg"
          },
          {
            "label": "Default",
            "value": ""
          },
          {
            "label": "Small",
            "value": "input-group-sm"
          },
          {
            "label": "Extra small",
            "value": "input-group-xm"
          }
        ]
      }
    ]
  }
}
